__init__.py
ftract.py
medirect.py
mefetch.py
medirect-0.34.0.dist-info/licenses/LICENSE
medirect-0.34.0.dist-info/METADATA
medirect-0.34.0.dist-info/WHEEL
medirect-0.34.0.dist-info/entry_points.txt
medirect-0.34.0.dist-info/top_level.txt
medirect-0.34.0.dist-info/RECORD
