Metadata-Version: 2.4
Name: medirect
Version: 0.34.0
Summary: Multithreaded ncbi edirect and ftract
Author-email: Chris Rosenthal <crosenth@gmail.com>
License:                     GNU GENERAL PUBLIC LICENSE
Project-URL: repository, https://github.com/crosenth/medirect
Keywords: bioinformatics,ncbi,edirect,entrez,multiprocessing,multithreading
Classifier: Environment :: Console
Classifier: Intended Audience :: End Users/Desktop
Classifier: Intended Audience :: Science/Research
Classifier: Operating System :: OS Independent
Classifier: Programming Language :: Python :: 3 :: Only
Requires-Python: >=3.9
License-File: LICENSE
Requires-Dist: biopython>=1.68
Requires-Dist: retrying>=1.3.3
Dynamic: license-file
